dbt_ext/__init__.py
dbt_ext/dbt_files/__init__.py
dbt_ext/dbt_files/bundle/transform/.gitignore
dbt_ext/dbt_files/bundle/transform/dbt_project.yml
dbt_ext/dbt_files/bundle/transform/models/.gitkeep
dbt_ext/dbt_files/profiles/athena/profiles.yml
dbt_ext/dbt_files/profiles/bigquery/profiles.yml
dbt_ext/dbt_files/profiles/duckdb/profiles.yml
dbt_ext/dbt_files/profiles/postgres/profiles.yml
dbt_ext/dbt_files/profiles/redshift/profiles.yml
dbt_ext/dbt_files/profiles/snowflake/profiles.yml
dbt_ext/extension.py
dbt_ext/main.py
dbt_ext/pass_through.py
meltano_dbt_ext-0.4.0.dist-info/METADATA
meltano_dbt_ext-0.4.0.dist-info/WHEEL
meltano_dbt_ext-0.4.0.dist-info/entry_points.txt
meltano_dbt_ext-0.4.0.dist-info/licenses/LICENSE
meltano_dbt_ext-0.4.0.dist-info/RECORD
