Metadata-Version: 2.4
Name: meltano-dbt-ext
Version: 0.4.0
Summary: A Meltano utility extension to manage dbt projects.
License: Apache-2.0
License-File: LICENSE
Author: Meltano Team and Contributors
Author-email: hello@meltano.com
Maintainer: Meltano Team and Contributors
Maintainer-email: hello@meltano.com
Requires-Python: >=3.10
Classifier: License :: OSI Approved :: Apache Software License
Classifier: Programming Language :: Python :: 3
Classifier: Programming Language :: Python :: 3.10
Classifier: Programming Language :: Python :: 3.11
Classifier: Programming Language :: Python :: 3.12
Classifier: Programming Language :: Python :: 3.13
Classifier: Programming Language :: Python :: 3.14
Requires-Dist: PyYAML (>=6.0.0)
Requires-Dist: click (>=8.3.0,<8.4.0)
Requires-Dist: meltano.edk (>=0.5.0,<0.6.0) ; python_version < "4"
Requires-Dist: typer (>=0.18.0,<0.19.0)
Project-URL: Homepage, https://meltano.com
Project-URL: Repository, https://github.com/meltano/dbt-ext
